speedict-0.3.12.dist-info/METADATA
speedict-0.3.12.dist-info/WHEEL
speedict-0.3.12.dist-info/license_files/LICENSE
speedict/py.typed
speedict/speedict.pyi
speedict/__init__.py
speedict/speedict.cp39-win32.pyd
speedict-0.3.12.dist-info/RECORD
